<?xml version="1.0" encoding="UTF-8"?>
<mappingtask>
  <config>
    <rewriteSubsumptions>true</rewriteSubsumptions>
    <rewriteCoverages>true</rewriteCoverages>
    <rewriteSelfJoins>true</rewriteSelfJoins>
    <rewriteEGDs>true</rewriteEGDs>
    <sortStrategy>-1</sortStrategy>
    <skolemTableStrategy>-1</skolemTableStrategy>
    <useLocalSkolem>false</useLocalSkolem>
  </config>
  <source>
    <type>relational</type>
    <relational>
      <driver>org.postgresql.Driver</driver>
      <uri>jdbc:postgresql://localhost:5432/spicy_40join</uri>
      <login>postgres</login>
      <password>postgres</password>
    </relational>
    <inclusions />
    <exclusions />
    <duplications />
    <functionalDependencies />
    <selectionConditions />
 
  <joinConditions>
 <joinCondition>
 <join>
<from>spicy_40join.relation_36.relation_36Tuple.attribute_76</from>
<to>spicy_40join.relation_37.relation_37Tuple.attribute_75</to>
</join> <foreignKey>true</foreignKey>
 <mandatory>true</mandatory>
</joinCondition>
 <joinCondition>
 <join>
<from>spicy_40join.relation_4.relation_4Tuple.attribute_44</from>
<to>spicy_40join.relation_5.relation_5Tuple.attribute_43</to>
</join> <foreignKey>true</foreignKey>
 <mandatory>true</mandatory>
</joinCondition>
 <joinCondition>
 <join>
<from>spicy_40join.relation_66.relation_66Tuple.attribute_106</from>
<to>spicy_40join.relation_67.relation_67Tuple.attribute_105</to>
</join> <foreignKey>true</foreignKey>
 <mandatory>true</mandatory>
</joinCondition>
 <joinCondition>
 <join>
<from>spicy_40join.relation_80.relation_80Tuple.attribute_120</from>
<to>spicy_40join.relation_79.relation_79Tuple.attribute_119</to>
</join> <foreignKey>true</foreignKey>
 <mandatory>true</mandatory>
</joinCondition>
 <joinCondition>
 <join>
<from>spicy_40join.relation_18.relation_18Tuple.attribute_58</from>
<to>spicy_40join.relation_19.relation_19Tuple.attribute_57</to>
</join> <foreignKey>true</foreignKey>
 <mandatory>true</mandatory>
</joinCondition>
 <joinCondition>
 <join>
<from>spicy_40join.relation_37.relation_37Tuple.attribute_77</from>
<to>spicy_40join.relation_40.relation_40Tuple.attribute_78</to>
</join> <foreignKey>true</foreignKey>
 <mandatory>true</mandatory>
</joinCondition>
 <joinCondition>
 <join>
<from>spicy_40join.relation_28.relation_28Tuple.attribute_68</from>
<to>spicy_40join.relation_30.relation_30Tuple.attribute_67</to>
</join> <foreignKey>true</foreignKey>
 <mandatory>true</mandatory>
</joinCondition>
 <joinCondition>
 <join>
<from>spicy_40join.relation_40.relation_40Tuple.attribute_80</from>
<to>spicy_40join.relation_42.relation_42Tuple.attribute_79</to>
</join> <foreignKey>true</foreignKey>
 <mandatory>true</mandatory>
</joinCondition>
 <joinCondition>
 <join>
<from>spicy_40join.relation_61.relation_61Tuple.attribute_101</from>
<to>spicy_40join.relation_64.relation_64Tuple.attribute_102</to>
</join> <foreignKey>true</foreignKey>
 <mandatory>true</mandatory>
</joinCondition>
 <joinCondition>
 <join>
<from>spicy_40join.relation_8.relation_8Tuple.attribute_48</from>
<to>spicy_40join.relation_10.relation_10Tuple.attribute_47</to>
</join> <foreignKey>true</foreignKey>
 <mandatory>true</mandatory>
</joinCondition>
 <joinCondition>
 <join>
<from>spicy_40join.relation_51.relation_51Tuple.attribute_91</from>
<to>spicy_40join.relation_54.relation_54Tuple.attribute_92</to>
</join> <foreignKey>true</foreignKey>
 <mandatory>true</mandatory>
</joinCondition>
 <joinCondition>
 <join>
<from>spicy_40join.relation_73.relation_73Tuple.attribute_113</from>
<to>spicy_40join.relation_76.relation_76Tuple.attribute_114</to>
</join> <foreignKey>true</foreignKey>
 <mandatory>true</mandatory>
</joinCondition>
 <joinCondition>
 <join>
<from>spicy_40join.relation_78.relation_78Tuple.attribute_118</from>
<to>spicy_40join.relation_80.relation_80Tuple.attribute_117</to>
</join> <foreignKey>true</foreignKey>
 <mandatory>true</mandatory>
</joinCondition>
 <joinCondition>
 <join>
<from>spicy_40join.relation_67.relation_67Tuple.attribute_107</from>
<to>spicy_40join.relation_70.relation_70Tuple.attribute_108</to>
</join> <foreignKey>true</foreignKey>
 <mandatory>true</mandatory>
</joinCondition>
 <joinCondition>
 <join>
<from>spicy_40join.relation_58.relation_58Tuple.attribute_98</from>
<to>spicy_40join.relation_60.relation_60Tuple.attribute_97</to>
</join> <foreignKey>true</foreignKey>
 <mandatory>true</mandatory>
</joinCondition>
 <joinCondition>
 <join>
<from>spicy_40join.relation_48.relation_48Tuple.attribute_88</from>
<to>spicy_40join.relation_50.relation_50Tuple.attribute_87</to>
</join> <foreignKey>true</foreignKey>
 <mandatory>true</mandatory>
</joinCondition>
 <joinCondition>
 <join>
<from>spicy_40join.relation_70.relation_70Tuple.attribute_110</from>
<to>spicy_40join.relation_72.relation_72Tuple.attribute_109</to>
</join> <foreignKey>true</foreignKey>
 <mandatory>true</mandatory>
</joinCondition>
 <joinCondition>
 <join>
<from>spicy_40join.relation_24.relation_24Tuple.attribute_64</from>
<to>spicy_40join.relation_26.relation_26Tuple.attribute_63</to>
</join> <foreignKey>true</foreignKey>
 <mandatory>true</mandatory>
</joinCondition>
 <joinCondition>
 <join>
<from>spicy_40join.relation_46.relation_46Tuple.attribute_86</from>
<to>spicy_40join.relation_48.relation_48Tuple.attribute_85</to>
</join> <foreignKey>true</foreignKey>
 <mandatory>true</mandatory>
</joinCondition>
 <joinCondition>
 <join>
<from>spicy_40join.relation_14.relation_14Tuple.attribute_54</from>
<to>spicy_40join.relation_16.relation_16Tuple.attribute_53</to>
</join> <foreignKey>true</foreignKey>
 <mandatory>true</mandatory>
</joinCondition>
 <joinCondition>
 <join>
<from>spicy_40join.relation_26.relation_26Tuple.attribute_66</from>
<to>spicy_40join.relation_28.relation_28Tuple.attribute_65</to>
</join> <foreignKey>true</foreignKey>
 <mandatory>true</mandatory>
</joinCondition>
 <joinCondition>
 <join>
<from>spicy_40join.relation_2.relation_2Tuple.attribute_42</from>
<to>spicy_40join.relation_4.relation_4Tuple.attribute_41</to>
</join> <foreignKey>true</foreignKey>
 <mandatory>true</mandatory>
</joinCondition>
 <joinCondition>
 <join>
<from>spicy_40join.relation_16.relation_16Tuple.attribute_56</from>
<to>spicy_40join.relation_18.relation_18Tuple.attribute_55</to>
</join> <foreignKey>true</foreignKey>
 <mandatory>true</mandatory>
</joinCondition>
 <joinCondition>
 <join>
<from>spicy_40join.relation_19.relation_19Tuple.attribute_59</from>
<to>spicy_40join.relation_22.relation_22Tuple.attribute_60</to>
</join> <foreignKey>true</foreignKey>
 <mandatory>true</mandatory>
</joinCondition>
 <joinCondition>
 <join>
<from>spicy_40join.relation_42.relation_42Tuple.attribute_82</from>
<to>spicy_40join.relation_44.relation_44Tuple.attribute_81</to>
</join> <foreignKey>true</foreignKey>
 <mandatory>true</mandatory>
</joinCondition>
 <joinCondition>
 <join>
<from>spicy_40join.relation_64.relation_64Tuple.attribute_104</from>
<to>spicy_40join.relation_66.relation_66Tuple.attribute_103</to>
</join> <foreignKey>true</foreignKey>
 <mandatory>true</mandatory>
</joinCondition>
 <joinCondition>
 <join>
<from>spicy_40join.relation_10.relation_10Tuple.attribute_50</from>
<to>spicy_40join.relation_12.relation_12Tuple.attribute_49</to>
</join> <foreignKey>true</foreignKey>
 <mandatory>true</mandatory>
</joinCondition>
 <joinCondition>
 <join>
<from>spicy_40join.relation_31.relation_31Tuple.attribute_71</from>
<to>spicy_40join.relation_34.relation_34Tuple.attribute_72</to>
</join> <foreignKey>true</foreignKey>
 <mandatory>true</mandatory>
</joinCondition>
 <joinCondition>
 <join>
<from>spicy_40join.relation_54.relation_54Tuple.attribute_94</from>
<to>spicy_40join.relation_56.relation_56Tuple.attribute_93</to>
</join> <foreignKey>true</foreignKey>
 <mandatory>true</mandatory>
</joinCondition>
 <joinCondition>
 <join>
<from>spicy_40join.relation_76.relation_76Tuple.attribute_116</from>
<to>spicy_40join.relation_78.relation_78Tuple.attribute_115</to>
</join> <foreignKey>true</foreignKey>
 <mandatory>true</mandatory>
</joinCondition>
 <joinCondition>
 <join>
<from>spicy_40join.relation_22.relation_22Tuple.attribute_62</from>
<to>spicy_40join.relation_24.relation_24Tuple.attribute_61</to>
</join> <foreignKey>true</foreignKey>
 <mandatory>true</mandatory>
</joinCondition>
 <joinCondition>
 <join>
<from>spicy_40join.relation_44.relation_44Tuple.attribute_84</from>
<to>spicy_40join.relation_46.relation_46Tuple.attribute_83</to>
</join> <foreignKey>true</foreignKey>
 <mandatory>true</mandatory>
</joinCondition>
 <joinCondition>
 <join>
<from>spicy_40join.relation_12.relation_12Tuple.attribute_52</from>
<to>spicy_40join.relation_14.relation_14Tuple.attribute_51</to>
</join> <foreignKey>true</foreignKey>
 <mandatory>true</mandatory>
</joinCondition>
 <joinCondition>
 <join>
<from>spicy_40join.relation_34.relation_34Tuple.attribute_74</from>
<to>spicy_40join.relation_36.relation_36Tuple.attribute_73</to>
</join> <foreignKey>true</foreignKey>
 <mandatory>true</mandatory>
</joinCondition>
 <joinCondition>
 <join>
<from>spicy_40join.relation_56.relation_56Tuple.attribute_96</from>
<to>spicy_40join.relation_58.relation_58Tuple.attribute_95</to>
</join> <foreignKey>true</foreignKey>
 <mandatory>true</mandatory>
</joinCondition>
 <joinCondition>
 <join>
<from>spicy_40join.relation_50.relation_50Tuple.attribute_90</from>
<to>spicy_40join.relation_51.relation_51Tuple.attribute_89</to>
</join> <foreignKey>true</foreignKey>
 <mandatory>true</mandatory>
</joinCondition>
 <joinCondition>
 <join>
<from>spicy_40join.relation_72.relation_72Tuple.attribute_112</from>
<to>spicy_40join.relation_73.relation_73Tuple.attribute_111</to>
</join> <foreignKey>true</foreignKey>
 <mandatory>true</mandatory>
</joinCondition>
 <joinCondition>
 <join>
<from>spicy_40join.relation_30.relation_30Tuple.attribute_70</from>
<to>spicy_40join.relation_31.relation_31Tuple.attribute_69</to>
</join> <foreignKey>true</foreignKey>
 <mandatory>true</mandatory>
</joinCondition>
 <joinCondition>
 <join>
<from>spicy_40join.relation_5.relation_5Tuple.attribute_45</from>
<to>spicy_40join.relation_8.relation_8Tuple.attribute_46</to>
</join> <foreignKey>true</foreignKey>
 <mandatory>true</mandatory>
</joinCondition>
 <joinCondition>
 <join>
<from>spicy_40join.relation_60.relation_60Tuple.attribute_100</from>
<to>spicy_40join.relation_61.relation_61Tuple.attribute_99</to>
</join> <foreignKey>true</foreignKey>
 <mandatory>true</mandatory>
</joinCondition>
 </joinConditions>



  </source>
  <target>
    <type>relational</type>
    <relational>
      <driver>org.postgresql.Driver</driver>
      <uri>jdbc:postgresql://localhost:5432/spicy_40join</uri>
      <login>postgres</login>
      <password>postgres</password>
    </relational>
    <inclusions />
    <exclusions />
    <duplications />
    <functionalDependencies />
    <selectionConditions />
    <joinConditions />
  </target>

 <correspondences>
<correspondence>
<source-paths>
<source-path>spicy_40join.relation_10.relation_10Tuple.attribute_4</source-path>
</source-paths>
<target-path>spicy_40join.relation_0.relation_0Tuple.attribute_4</target-path>
<transformation-function>spicy_40join.relation_10.relation_10Tuple.attribute_4</transformation-function>
 <confidence>1.0</confidence>
</correspondence>
<correspondence>
<source-paths>
<source-path>spicy_40join.relation_12.relation_12Tuple.attribute_5</source-path>
</source-paths>
<target-path>spicy_40join.relation_0.relation_0Tuple.attribute_5</target-path>
<transformation-function>spicy_40join.relation_12.relation_12Tuple.attribute_5</transformation-function>
 <confidence>1.0</confidence>
</correspondence>
<correspondence>
<source-paths>
<source-path>spicy_40join.relation_14.relation_14Tuple.attribute_6</source-path>
</source-paths>
<target-path>spicy_40join.relation_0.relation_0Tuple.attribute_6</target-path>
<transformation-function>spicy_40join.relation_14.relation_14Tuple.attribute_6</transformation-function>
 <confidence>1.0</confidence>
</correspondence>
<correspondence>
<source-paths>
<source-path>spicy_40join.relation_16.relation_16Tuple.attribute_7</source-path>
</source-paths>
<target-path>spicy_40join.relation_0.relation_0Tuple.attribute_7</target-path>
<transformation-function>spicy_40join.relation_16.relation_16Tuple.attribute_7</transformation-function>
 <confidence>1.0</confidence>
</correspondence>
<correspondence>
<source-paths>
<source-path>spicy_40join.relation_18.relation_18Tuple.attribute_8</source-path>
</source-paths>
<target-path>spicy_40join.relation_0.relation_0Tuple.attribute_8</target-path>
<transformation-function>spicy_40join.relation_18.relation_18Tuple.attribute_8</transformation-function>
 <confidence>1.0</confidence>
</correspondence>
<correspondence>
<source-paths>
<source-path>spicy_40join.relation_19.relation_19Tuple.attribute_9</source-path>
</source-paths>
<target-path>spicy_40join.relation_0.relation_0Tuple.attribute_9</target-path>
<transformation-function>spicy_40join.relation_19.relation_19Tuple.attribute_9</transformation-function>
 <confidence>1.0</confidence>
</correspondence>
<correspondence>
<source-paths>
<source-path>spicy_40join.relation_2.relation_2Tuple.attribute_0</source-path>
</source-paths>
<target-path>spicy_40join.relation_0.relation_0Tuple.attribute_0</target-path>
<transformation-function>spicy_40join.relation_2.relation_2Tuple.attribute_0</transformation-function>
 <confidence>1.0</confidence>
</correspondence>
<correspondence>
<source-paths>
<source-path>spicy_40join.relation_22.relation_22Tuple.attribute_10</source-path>
</source-paths>
<target-path>spicy_40join.relation_0.relation_0Tuple.attribute_10</target-path>
<transformation-function>spicy_40join.relation_22.relation_22Tuple.attribute_10</transformation-function>
 <confidence>1.0</confidence>
</correspondence>
<correspondence>
<source-paths>
<source-path>spicy_40join.relation_24.relation_24Tuple.attribute_11</source-path>
</source-paths>
<target-path>spicy_40join.relation_0.relation_0Tuple.attribute_11</target-path>
<transformation-function>spicy_40join.relation_24.relation_24Tuple.attribute_11</transformation-function>
 <confidence>1.0</confidence>
</correspondence>
<correspondence>
<source-paths>
<source-path>spicy_40join.relation_26.relation_26Tuple.attribute_12</source-path>
</source-paths>
<target-path>spicy_40join.relation_0.relation_0Tuple.attribute_12</target-path>
<transformation-function>spicy_40join.relation_26.relation_26Tuple.attribute_12</transformation-function>
 <confidence>1.0</confidence>
</correspondence>
<correspondence>
<source-paths>
<source-path>spicy_40join.relation_28.relation_28Tuple.attribute_13</source-path>
</source-paths>
<target-path>spicy_40join.relation_0.relation_0Tuple.attribute_13</target-path>
<transformation-function>spicy_40join.relation_28.relation_28Tuple.attribute_13</transformation-function>
 <confidence>1.0</confidence>
</correspondence>
<correspondence>
<source-paths>
<source-path>spicy_40join.relation_30.relation_30Tuple.attribute_14</source-path>
</source-paths>
<target-path>spicy_40join.relation_0.relation_0Tuple.attribute_14</target-path>
<transformation-function>spicy_40join.relation_30.relation_30Tuple.attribute_14</transformation-function>
 <confidence>1.0</confidence>
</correspondence>
<correspondence>
<source-paths>
<source-path>spicy_40join.relation_31.relation_31Tuple.attribute_15</source-path>
</source-paths>
<target-path>spicy_40join.relation_0.relation_0Tuple.attribute_15</target-path>
<transformation-function>spicy_40join.relation_31.relation_31Tuple.attribute_15</transformation-function>
 <confidence>1.0</confidence>
</correspondence>
<correspondence>
<source-paths>
<source-path>spicy_40join.relation_34.relation_34Tuple.attribute_16</source-path>
</source-paths>
<target-path>spicy_40join.relation_0.relation_0Tuple.attribute_16</target-path>
<transformation-function>spicy_40join.relation_34.relation_34Tuple.attribute_16</transformation-function>
 <confidence>1.0</confidence>
</correspondence>
<correspondence>
<source-paths>
<source-path>spicy_40join.relation_36.relation_36Tuple.attribute_17</source-path>
</source-paths>
<target-path>spicy_40join.relation_0.relation_0Tuple.attribute_17</target-path>
<transformation-function>spicy_40join.relation_36.relation_36Tuple.attribute_17</transformation-function>
 <confidence>1.0</confidence>
</correspondence>
<correspondence>
<source-paths>
<source-path>spicy_40join.relation_37.relation_37Tuple.attribute_18</source-path>
</source-paths>
<target-path>spicy_40join.relation_0.relation_0Tuple.attribute_18</target-path>
<transformation-function>spicy_40join.relation_37.relation_37Tuple.attribute_18</transformation-function>
 <confidence>1.0</confidence>
</correspondence>
<correspondence>
<source-paths>
<source-path>spicy_40join.relation_4.relation_4Tuple.attribute_1</source-path>
</source-paths>
<target-path>spicy_40join.relation_0.relation_0Tuple.attribute_1</target-path>
<transformation-function>spicy_40join.relation_4.relation_4Tuple.attribute_1</transformation-function>
 <confidence>1.0</confidence>
</correspondence>
<correspondence>
<source-paths>
<source-path>spicy_40join.relation_40.relation_40Tuple.attribute_19</source-path>
</source-paths>
<target-path>spicy_40join.relation_0.relation_0Tuple.attribute_19</target-path>
<transformation-function>spicy_40join.relation_40.relation_40Tuple.attribute_19</transformation-function>
 <confidence>1.0</confidence>
</correspondence>
<correspondence>
<source-paths>
<source-path>spicy_40join.relation_42.relation_42Tuple.attribute_20</source-path>
</source-paths>
<target-path>spicy_40join.relation_0.relation_0Tuple.attribute_20</target-path>
<transformation-function>spicy_40join.relation_42.relation_42Tuple.attribute_20</transformation-function>
 <confidence>1.0</confidence>
</correspondence>
<correspondence>
<source-paths>
<source-path>spicy_40join.relation_44.relation_44Tuple.attribute_21</source-path>
</source-paths>
<target-path>spicy_40join.relation_0.relation_0Tuple.attribute_21</target-path>
<transformation-function>spicy_40join.relation_44.relation_44Tuple.attribute_21</transformation-function>
 <confidence>1.0</confidence>
</correspondence>
<correspondence>
<source-paths>
<source-path>spicy_40join.relation_46.relation_46Tuple.attribute_22</source-path>
</source-paths>
<target-path>spicy_40join.relation_0.relation_0Tuple.attribute_22</target-path>
<transformation-function>spicy_40join.relation_46.relation_46Tuple.attribute_22</transformation-function>
 <confidence>1.0</confidence>
</correspondence>
<correspondence>
<source-paths>
<source-path>spicy_40join.relation_48.relation_48Tuple.attribute_23</source-path>
</source-paths>
<target-path>spicy_40join.relation_0.relation_0Tuple.attribute_23</target-path>
<transformation-function>spicy_40join.relation_48.relation_48Tuple.attribute_23</transformation-function>
 <confidence>1.0</confidence>
</correspondence>
<correspondence>
<source-paths>
<source-path>spicy_40join.relation_5.relation_5Tuple.attribute_2</source-path>
</source-paths>
<target-path>spicy_40join.relation_0.relation_0Tuple.attribute_2</target-path>
<transformation-function>spicy_40join.relation_5.relation_5Tuple.attribute_2</transformation-function>
 <confidence>1.0</confidence>
</correspondence>
<correspondence>
<source-paths>
<source-path>spicy_40join.relation_50.relation_50Tuple.attribute_24</source-path>
</source-paths>
<target-path>spicy_40join.relation_0.relation_0Tuple.attribute_24</target-path>
<transformation-function>spicy_40join.relation_50.relation_50Tuple.attribute_24</transformation-function>
 <confidence>1.0</confidence>
</correspondence>
<correspondence>
<source-paths>
<source-path>spicy_40join.relation_51.relation_51Tuple.attribute_25</source-path>
</source-paths>
<target-path>spicy_40join.relation_0.relation_0Tuple.attribute_25</target-path>
<transformation-function>spicy_40join.relation_51.relation_51Tuple.attribute_25</transformation-function>
 <confidence>1.0</confidence>
</correspondence>
<correspondence>
<source-paths>
<source-path>spicy_40join.relation_54.relation_54Tuple.attribute_26</source-path>
</source-paths>
<target-path>spicy_40join.relation_0.relation_0Tuple.attribute_26</target-path>
<transformation-function>spicy_40join.relation_54.relation_54Tuple.attribute_26</transformation-function>
 <confidence>1.0</confidence>
</correspondence>
<correspondence>
<source-paths>
<source-path>spicy_40join.relation_56.relation_56Tuple.attribute_27</source-path>
</source-paths>
<target-path>spicy_40join.relation_0.relation_0Tuple.attribute_27</target-path>
<transformation-function>spicy_40join.relation_56.relation_56Tuple.attribute_27</transformation-function>
 <confidence>1.0</confidence>
</correspondence>
<correspondence>
<source-paths>
<source-path>spicy_40join.relation_58.relation_58Tuple.attribute_28</source-path>
</source-paths>
<target-path>spicy_40join.relation_0.relation_0Tuple.attribute_28</target-path>
<transformation-function>spicy_40join.relation_58.relation_58Tuple.attribute_28</transformation-function>
 <confidence>1.0</confidence>
</correspondence>
<correspondence>
<source-paths>
<source-path>spicy_40join.relation_60.relation_60Tuple.attribute_29</source-path>
</source-paths>
<target-path>spicy_40join.relation_0.relation_0Tuple.attribute_29</target-path>
<transformation-function>spicy_40join.relation_60.relation_60Tuple.attribute_29</transformation-function>
 <confidence>1.0</confidence>
</correspondence>
<correspondence>
<source-paths>
<source-path>spicy_40join.relation_61.relation_61Tuple.attribute_30</source-path>
</source-paths>
<target-path>spicy_40join.relation_0.relation_0Tuple.attribute_30</target-path>
<transformation-function>spicy_40join.relation_61.relation_61Tuple.attribute_30</transformation-function>
 <confidence>1.0</confidence>
</correspondence>
<correspondence>
<source-paths>
<source-path>spicy_40join.relation_64.relation_64Tuple.attribute_31</source-path>
</source-paths>
<target-path>spicy_40join.relation_0.relation_0Tuple.attribute_31</target-path>
<transformation-function>spicy_40join.relation_64.relation_64Tuple.attribute_31</transformation-function>
 <confidence>1.0</confidence>
</correspondence>
<correspondence>
<source-paths>
<source-path>spicy_40join.relation_66.relation_66Tuple.attribute_32</source-path>
</source-paths>
<target-path>spicy_40join.relation_0.relation_0Tuple.attribute_32</target-path>
<transformation-function>spicy_40join.relation_66.relation_66Tuple.attribute_32</transformation-function>
 <confidence>1.0</confidence>
</correspondence>
<correspondence>
<source-paths>
<source-path>spicy_40join.relation_67.relation_67Tuple.attribute_33</source-path>
</source-paths>
<target-path>spicy_40join.relation_0.relation_0Tuple.attribute_33</target-path>
<transformation-function>spicy_40join.relation_67.relation_67Tuple.attribute_33</transformation-function>
 <confidence>1.0</confidence>
</correspondence>
<correspondence>
<source-paths>
<source-path>spicy_40join.relation_70.relation_70Tuple.attribute_34</source-path>
</source-paths>
<target-path>spicy_40join.relation_0.relation_0Tuple.attribute_34</target-path>
<transformation-function>spicy_40join.relation_70.relation_70Tuple.attribute_34</transformation-function>
 <confidence>1.0</confidence>
</correspondence>
<correspondence>
<source-paths>
<source-path>spicy_40join.relation_72.relation_72Tuple.attribute_35</source-path>
</source-paths>
<target-path>spicy_40join.relation_0.relation_0Tuple.attribute_35</target-path>
<transformation-function>spicy_40join.relation_72.relation_72Tuple.attribute_35</transformation-function>
 <confidence>1.0</confidence>
</correspondence>
<correspondence>
<source-paths>
<source-path>spicy_40join.relation_73.relation_73Tuple.attribute_36</source-path>
</source-paths>
<target-path>spicy_40join.relation_0.relation_0Tuple.attribute_36</target-path>
<transformation-function>spicy_40join.relation_73.relation_73Tuple.attribute_36</transformation-function>
 <confidence>1.0</confidence>
</correspondence>
<correspondence>
<source-paths>
<source-path>spicy_40join.relation_76.relation_76Tuple.attribute_37</source-path>
</source-paths>
<target-path>spicy_40join.relation_0.relation_0Tuple.attribute_37</target-path>
<transformation-function>spicy_40join.relation_76.relation_76Tuple.attribute_37</transformation-function>
 <confidence>1.0</confidence>
</correspondence>
<correspondence>
<source-paths>
<source-path>spicy_40join.relation_78.relation_78Tuple.attribute_38</source-path>
</source-paths>
<target-path>spicy_40join.relation_0.relation_0Tuple.attribute_38</target-path>
<transformation-function>spicy_40join.relation_78.relation_78Tuple.attribute_38</transformation-function>
 <confidence>1.0</confidence>
</correspondence>
<correspondence>
<source-paths>
<source-path>spicy_40join.relation_79.relation_79Tuple.attribute_40</source-path>
</source-paths>
<target-path>spicy_40join.relation_0.relation_0Tuple.attribute_40</target-path>
<transformation-function>spicy_40join.relation_79.relation_79Tuple.attribute_40</transformation-function>
 <confidence>1.0</confidence>
</correspondence>
<correspondence>
<source-paths>
<source-path>spicy_40join.relation_8.relation_8Tuple.attribute_3</source-path>
</source-paths>
<target-path>spicy_40join.relation_0.relation_0Tuple.attribute_3</target-path>
<transformation-function>spicy_40join.relation_8.relation_8Tuple.attribute_3</transformation-function>
 <confidence>1.0</confidence>
</correspondence>
<correspondence>
<source-paths>
<source-path>spicy_40join.relation_80.relation_80Tuple.attribute_39</source-path>
</source-paths>
<target-path>spicy_40join.relation_0.relation_0Tuple.attribute_39</target-path>
<transformation-function>spicy_40join.relation_80.relation_80Tuple.attribute_39</transformation-function>
 <confidence>1.0</confidence>
</correspondence>
</correspondences>


 
</mappingtask>

