 <joinConditions>
 <joinCondition>
 <join>
<from>lara_manlon_dep.olm_openaddresses.olm_openaddressesTuple.postcode</from>
<to>lara_manlon_dep.unique_openaddresses.unique_openaddressesTuple.postcode</to>
</join> <foreignKey>true</foreignKey>
 <mandatory>true</mandatory>
</joinCondition>
 <joinCondition>
 <join>
<from>lara_manlon_dep.l_belvoir.l_belvoirTuple.postcode</from>
<to>lara_manlon_dep.l_deprivation.l_deprivationTuple.postcode</to>
</join> <foreignKey>true</foreignKey>
 <mandatory>true</mandatory>
</joinCondition>
 <joinCondition>
 <join>
<from>lara_manlon_dep.m_belvoir.m_belvoirTuple.postcode</from>
<to>lara_manlon_dep.m_deprivation.m_deprivationTuple.postcode</to>
</join> <foreignKey>true</foreignKey>
 <mandatory>true</mandatory>
</joinCondition>
 <joinCondition>
 <join>
<from>lara_manlon_dep.m_agent.m_agentTuple.city</from>
<to>lara_manlon_dep.m_agent.m_agentTuple.street</to>
</join> <foreignKey>true</foreignKey>
 <mandatory>true</mandatory>
</joinCondition>
 <joinCondition>
 <join>
<from>lara_manlon_dep.m_agent.m_agentTuple.city</from>
<to>lara_manlon_dep.m_agent.m_agentTuple.street</to>
</join> <foreignKey>true</foreignKey>
 <mandatory>true</mandatory>
</joinCondition>
 <joinCondition>
 <join>
<from>lara_manlon_dep.m_agent.m_agentTuple.street</from>
<to>lara_manlon_dep.m_agent.m_agentTuple.city</to>
</join> <foreignKey>true</foreignKey>
 <mandatory>true</mandatory>
</joinCondition>
 <joinCondition>
 <join>
<from>lara_manlon_dep.m_agent.m_agentTuple.street</from>
<to>lara_manlon_dep.m_agent.m_agentTuple.city</to>
</join> <foreignKey>true</foreignKey>
 <mandatory>true</mandatory>
</joinCondition>
 </joinConditions>
